fiducials.py
fiducials-0.dist-info/METADATA
fiducials-0.dist-info/WHEEL
fiducials-0.dist-info/top_level.txt
fiducials-0.dist-info/RECORD
