Metadata-Version: 2.4
Name: fiducials
Version: 0
Summary: unified interface to many fiducial marker detectors
Classifier: Operating System :: OS Independent
Classifier: Topic :: Scientific/Engineering :: Image Processing
Classifier: Topic :: Scientific/Engineering :: Mathematics
Dynamic: classifier
Dynamic: summary
